Rankcard/Main.py
Rankcard/__init__.py
Python_discord_rankcard-0.0.6.dist-info/LICENSE
Python_discord_rankcard-0.0.6.dist-info/METADATA
Python_discord_rankcard-0.0.6.dist-info/WHEEL
Python_discord_rankcard-0.0.6.dist-info/top_level.txt
Python_discord_rankcard-0.0.6.dist-info/RECORD
