Metadata-Version: 2.1
Name: Python-discord-rankcard
Version: 0.0.6
Summary: A simple discord rank card written in python.
Home-page: https://github.com/yangman946/Python-discord-rankcard
Author: yangman946
Author-email: clarenceyang284@gmail.com
License: UNKNOWN
Keywords: python,pillow,discord,discord-py
Platform: UNKNOWN
Classifier: Development Status :: 5 - Production/Stable
Classifier: Intended Audience :: Developers
Classifier: Programming Language :: Python :: 3
Classifier: Operating System :: Unix
Classifier: License :: OSI Approved :: MIT License
Classifier: Operating System :: MacOS :: MacOS X
Classifier: Operating System :: Microsoft :: Windows
License-File: LICENSE
Requires-Dist: Pillow
Requires-Dist: requests
